nPDyn/__init__.py
nPDyn/_version.py
nPDyn/dataset.py
nPDyn/fileFormatParser.py
nPDyn/helpers.py
nPDyn/sample.py
nPDyn/dataManipulation/__init__.py
nPDyn/dataManipulation/binData.py
nPDyn/dataManipulation/slidingAverage.py
nPDyn/dataParsers/__init__.py
nPDyn/dataParsers/groupScans.py
nPDyn/dataParsers/in16b_bats_scans_reduction.py
nPDyn/dataParsers/in16b_fws_scans_reduction.py
nPDyn/dataParsers/in16b_nexus.py
nPDyn/dataParsers/in16b_qens_scans_reduction.py
nPDyn/dataParsers/inxConvert.py
nPDyn/dataParsers/mantidNexus.py
nPDyn/dataParsers/mantidWorkspace.py
nPDyn/dataParsers/stringParser.py
nPDyn/dataParsers/xml_detector_grouping.py
nPDyn/dataParsers/instruments/__init__.py
nPDyn/dataParsers/instruments/in16b.py
nPDyn/dataTypes/__init__.py
nPDyn/dataTypes/baseType.py
nPDyn/dataTypes/fwsType.py
nPDyn/dataTypes/qensType.py
nPDyn/lib/__init__.py
nPDyn/lib/pyabsco.cpython-39-x86_64-linux-gnu.so
nPDyn/lmfit/__init__.py
nPDyn/lmfit/convolutions.py
nPDyn/lmfit/convolvedModel.py
nPDyn/lmfit/lmfit_builtins.py
nPDyn/lmfit/lmfit_presets.py
nPDyn/models/__init__.py
nPDyn/models/builtins.py
nPDyn/models/model.py
nPDyn/models/params.py
nPDyn/models/presets.py
nPDyn/models/d2O_calibration/D2O_interpolation_table.dat
nPDyn/models/d2O_calibration/D2O_temperatures.dat
nPDyn/models/d2O_calibration/__init__.py
nPDyn/models/d2O_calibration/interpD2O.py
nPDyn/plot/__init__.py
nPDyn/plot/create_window.py
nPDyn/plot/fwsPlot.py
nPDyn/plot/interactive_legend.py
nPDyn/plot/plot.py
nPDyn/plot/qensPlot.py
nPDyn/plot/subPlotsFormat.py
nPDyn-3.0.0.dist-info/LICENSE
nPDyn-3.0.0.dist-info/METADATA
nPDyn-3.0.0.dist-info/WHEEL
nPDyn-3.0.0.dist-info/top_level.txt
nPDyn-3.0.0.dist-info/RECORD
