Metadata-Version: 2.1
Name: nPDyn
Version: 3.0.0
Summary: Python package for analysis of neutron backscattering data
Home-page: https://github.com/kpounot/nPDyn
Author: Kevin Pounot
Author-email: kpounot@hotmail.fr
License: UNKNOWN
Platform: Windows
Platform: Linux
Platform: Mac OS X
Classifier: Development Status :: 5 - Production/Stable
Classifier: License :: OSI Approved :: GNU General Public License v3 or later (GPLv3+)
Classifier: Intended Audience :: Science/Research
Classifier: Operating System :: OS Independent
Classifier: Programming Language :: Python :: 3.6
Classifier: Programming Language :: Python :: 3.7
Classifier: Programming Language :: Python :: 3.8
Classifier: Programming Language :: Python :: 3.9
Classifier: Topic :: Scientific/Engineering
Requires-Dist: CythonGSL
Requires-Dist: cython
Requires-Dist: scipy
Requires-Dist: numpy
Requires-Dist: matplotlib
Requires-Dist: PyQt5
Requires-Dist: h5py
Requires-Dist: lmfit
Requires-Dist: defusedxml
Requires-Dist: qtwidgets
